{
  "composites": [
    {
      "name": "XF",
      "viscosity": "high",
      "polymerization_shrinkage_percent": 2.5,
      "microhardness_KHN": 74.34,
      "filler_content_percent": 85,
      "wear_resistance": "high",
      "depth_of_cure_mm": 4.5,
      "matrix_type": "methacrylate",
      "suitable_for_occlusal": true,
      "requires_capping": false,
      "category": "high_viscosity_bulk_fill",
      "region": "international",
      "manufacturer": "Dentsply Sirona",
      "notes": "Высокая микротвердость, подходит для жевательных зубов",
      "year_released": 2015,
      "price_rub": 4500
    },
    {
      "name": "TBF",
      "viscosity": "high",
      "polymerization_shrinkage_percent": 2.0,
      "microhardness_KHN": 50.89,
      "filler_content_percent": 75,
      "wear_resistance": "high",
      "depth_of_cure_mm": 4.5,
      "matrix_type": "methacrylate",
      "suitable_for_occlusal": true,
      "requires_capping": false,
      "category": "high_viscosity_bulk_fill",
      "region": "international",
      "manufacturer": "Ivoclar Vivadent",
      "notes": "Подходит для жевательных зубов",
      "year_released": 2013,
      "price_rub": 3800
    },
    {
      "name": "FBP",
      "viscosity": "high",
      "polymerization_shrinkage_percent": 2.2,
      "microhardness_KHN": 49.6,
      "filler_content_percent": 70,
      "wear_resistance": "high",
      "depth_of_cure_mm": 4.5,
      "matrix_type": "methacrylate",
      "suitable_for_occlusal": true,
      "requires_capping": false,
      "category": "high_viscosity_bulk_fill",
      "region": "international",
      "manufacturer": "3M ESPE",
      "notes": "Подходит для жевательных зубов",
      "year_released": 2013,
      "price_rub": 4200
    },
    {
      "name": "ADM",
      "viscosity": "high",
      "polymerization_shrinkage_percent": 1.5,
      "microhardness_KHN": 37.36,
      "filler_content_percent": 65,
      "wear_resistance": "medium",
      "depth_of_cure_mm": 4.5,
      "matrix_type": "ormocer",
      "suitable_for_occlusal": false,
      "requires_capping": true,
      "category": "high_viscosity_bulk_fill",
      "region": "international",
      "manufacturer": "Voco",
      "notes": "Ormocer матрица, низкая микротвердость, не рекомендуется для окклюзионных поверхностей",
      "year_released": 2016,
      "price_rub": 3500
    },
    {
      "name": "Z3XT",
      "viscosity": "high",
      "polymerization_shrinkage_percent": 3.07,
      "microhardness_KHN": 89.37,
      "filler_content_percent": 89,
      "wear_resistance": "very_high",
      "depth_of_cure_mm": 2.63,
      "matrix_type": "methacrylate",
      "suitable_for_occlusal": true,
      "requires_capping": false,
      "category": "conventional",
      "region": "international",
      "manufacturer": "3M ESPE",
      "notes": "Традиционный композит, высокая микротвердость, ограниченная глубина полимеризации",
      "year_released": 2008,
      "price_rub": 3200
    },
    {
      "name": "Z3F",
      "viscosity": "low",
      "polymerization_shrinkage_percent": 3.84,
      "microhardness_KHN": 33.31,
      "filler_content_percent": 60,
      "wear_resistance": "low",
      "depth_of_cure_mm": 3.63,
      "matrix_type": "methacrylate",
      "suitable_for_occlusal": false,
      "requires_capping": true,
      "category": "low_viscosity_bulk_fill",
      "region": "international",
      "manufacturer": "3M ESPE",
      "notes": "НЕ подходит для жевательных зубов, требует покрытия, исключен из выбора",
      "year_released": 2015,
      "price_rub": 3000
    },
    {
      "name": "XB",
      "viscosity": "low",
      "polymerization_shrinkage_percent": 4.5,
      "microhardness_KHN": 31.95,
      "filler_content_percent": 55,
      "wear_resistance": "low",
      "depth_of_cure_mm": 4.5,
      "matrix_type": "methacrylate",
      "suitable_for_occlusal": false,
      "requires_capping": true,
      "category": "low_viscosity_bulk_fill",
      "region": "international",
      "manufacturer": "Dentsply Sirona",
      "notes": "НЕ подходит для жевательных зубов, требует покрытия, исключен из выбора",
      "year_released": 2015,
      "price_rub": 3000
    },
    {
      "name": "SDR",
      "viscosity": "low",
      "polymerization_shrinkage_percent": 2.8,
      "microhardness_KHN": 35.5,
      "filler_content_percent": 48,
      "wear_resistance": "medium",
      "depth_of_cure_mm": 4.0,
      "matrix_type": "methacrylate",
      "suitable_for_occlusal": false,
      "requires_capping": true,
      "category": "low_viscosity_bulk_fill",
      "region": "international",
      "manufacturer": "Dentsply Sirona",
      "notes": "Flowable bulk-fill композит Smart Dentin Replacement. Используется как базовый/лайнерный слой. Снижение полимеризационного стресса на 60% по сравнению с обычными flowable. Требует покрытия композитом для окклюзионных поверхностей",
      "year_released": 2012,
      "price_rub": 3500
    },
    {
      "name": "SDR flow+",
      "viscosity": "low",
      "polymerization_shrinkage_percent": 2.5,
      "microhardness_KHN": 42.0,
      "filler_content_percent": 52,
      "wear_resistance": "medium",
      "depth_of_cure_mm": 4.0,
      "matrix_type": "methacrylate",
      "suitable_for_occlusal": false,
      "requires_capping": true,
      "category": "low_viscosity_bulk_fill",
      "region": "international",
      "manufacturer": "Dentsply Sirona",
      "notes": "Улучшенная версия SDR. Повышенная износостойкость и рентгеноконтрастность по сравнению с оригинальным SDR. Flowable bulk-fill композит для использования в качестве базового слоя. Требует покрытия для окклюзионных поверхностей",
      "year_released": 2018,
      "price_rub": 3800
    },
    {
      "name": "Filtek Supreme Ultra",
      "viscosity": "high",
      "polymerization_shrinkage_percent": 2.8,
      "microhardness_KHN": 82.5,
      "filler_content_percent": 78,
      "wear_resistance": "very_high",
      "depth_of_cure_mm": 2.5,
      "matrix_type": "methacrylate",
      "suitable_for_occlusal": true,
      "requires_capping": false,
      "category": "nanocomposite",
      "region": "USA",
      "manufacturer": "3M ESPE",
      "notes": "Нанокомпозит, популярен в США, высокая прочность и эстетика",
      "year_released": 2010,
      "price_rub": 4800
    },
    {
      "name": "Aelite Aesthetic Enamel",
      "viscosity": "high",
      "polymerization_shrinkage_percent": 2.6,
      "microhardness_KHN": 75.2,
      "filler_content_percent": 76,
      "wear_resistance": "high",
      "depth_of_cure_mm": 2.8,
      "matrix_type": "methacrylate",
      "suitable_for_occlusal": true,
      "requires_capping": false,
      "category": "nanocomposite",
      "region": "USA",
      "manufacturer": "Bisco",
      "notes": "Высокоэстетичный нанокомпозит, широко используется в США",
      "year_released": 2012,
      "price_rub": 2800
    },
    {
      "name": "Aelite All-Purpose Body",
      "viscosity": "high",
      "polymerization_shrinkage_percent": 2.4,
      "microhardness_KHN": 68.3,
      "filler_content_percent": 72,
      "wear_resistance": "high",
      "depth_of_cure_mm": 3.0,
      "matrix_type": "methacrylate",
      "suitable_for_occlusal": true,
      "requires_capping": false,
      "category": "microhybrid",
      "region": "USA",
      "manufacturer": "Bisco",
      "notes": "Универсальный микрогибридный композит, популярен в США",
      "year_released": 2015,
      "price_rub": 3000
    },
    {
      "name": "Estelite Sigma Quick",
      "viscosity": "high",
      "polymerization_shrinkage_percent": 2.3,
      "microhardness_KHN": 71.8,
      "filler_content_percent": 74,
      "wear_resistance": "high",
      "depth_of_cure_mm": 2.7,
      "matrix_type": "methacrylate",
      "suitable_for_occlusal": true,
      "requires_capping": false,
      "category": "nanocomposite",
      "region": "USA",
      "manufacturer": "Tokuyama Dental",
      "notes": "Быстрая полимеризация, популярен в США и Азии",
      "year_released": 2014,
      "price_rub": 3100
    },
    {
      "name": "ДентЛайт",
      "viscosity": "high",
      "polymerization_shrinkage_percent": 2.7,
      "microhardness_KHN": 65.4,
      "filler_content_percent": 70,
      "wear_resistance": "high",
      "depth_of_cure_mm": 3.2,
      "matrix_type": "methacrylate",
      "suitable_for_occlusal": true,
      "requires_capping": false,
      "category": "microhybrid",
      "region": "Russia",
      "manufacturer": "ОЭЗ ВладМиВа",
      "notes": "Российский микрогибридный композит, высокая пластичность",
      "year_released": 2015,
      "price_rub": 2500
    },
    {
      "name": "Омега Дент Универсал",
      "viscosity": "high",
      "polymerization_shrinkage_percent": 2.5,
      "microhardness_KHN": 67.2,
      "filler_content_percent": 68,
      "wear_resistance": "high",
      "depth_of_cure_mm": 3.0,
      "matrix_type": "methacrylate",
      "suitable_for_occlusal": true,
      "requires_capping": false,
      "category": "microhybrid",
      "region": "Russia",
      "manufacturer": "Омега Дент",
      "notes": "Российский универсальный композит, не уступает зарубежным аналогам",
      "year_released": 2016,
      "price_rub": 2200
    },
    {
      "name": "Charisma",
      "viscosity": "high",
      "polymerization_shrinkage_percent": 2.6,
      "microhardness_KHN": 69.5,
      "filler_content_percent": 71,
      "wear_resistance": "high",
      "depth_of_cure_mm": 2.9,
      "matrix_type": "methacrylate",
      "suitable_for_occlusal": true,
      "requires_capping": false,
      "category": "microhybrid",
      "region": "Russia",
      "manufacturer": "Heraeus Kulzer",
      "notes": "Популярен в России, хорошее соотношение цена-качество",
      "year_released": 2011,
      "price_rub": 2900
    },
    {
      "name": "GrandioSO",
      "viscosity": "high",
      "polymerization_shrinkage_percent": 2.1,
      "microhardness_KHN": 73.8,
      "filler_content_percent": 77,
      "wear_resistance": "very_high",
      "depth_of_cure_mm": 2.6,
      "matrix_type": "methacrylate",
      "suitable_for_occlusal": true,
      "requires_capping": false,
      "category": "nanocomposite",
      "region": "Italy",
      "manufacturer": "Voco",
      "notes": "Немецкий производитель, популярен в Италии, нанокомпозит",
      "year_released": 2013,
      "price_rub": 3600
    },
    {
      "name": "Enamel Plus HFO",
      "viscosity": "high",
      "polymerization_shrinkage_percent": 2.4,
      "microhardness_KHN": 70.6,
      "filler_content_percent": 73,
      "wear_resistance": "high",
      "depth_of_cure_mm": 2.8,
      "matrix_type": "methacrylate",
      "suitable_for_occlusal": true,
      "requires_capping": false,
      "category": "microhybrid",
      "region": "Italy",
      "manufacturer": "Micerium",
      "notes": "Итальянский производитель, высокое качество",
      "year_released": 2014,
      "price_rub": 3400
    },
    {
      "name": "G-aenial",
      "viscosity": "high",
      "polymerization_shrinkage_percent": 2.2,
      "microhardness_KHN": 72.4,
      "filler_content_percent": 75,
      "wear_resistance": "high",
      "depth_of_cure_mm": 2.7,
      "matrix_type": "methacrylate",
      "suitable_for_occlusal": true,
      "requires_capping": false,
      "category": "nanocomposite",
      "region": "Asia",
      "manufacturer": "GC Corporation",
      "notes": "Японский производитель, популярен в Азии, нанокомпозит",
      "year_released": 2015,
      "price_rub": 3300
    },
    {
      "name": "Beautiful II",
      "viscosity": "high",
      "polymerization_shrinkage_percent": 2.3,
      "microhardness_KHN": 68.9,
      "filler_content_percent": 72,
      "wear_resistance": "high",
      "depth_of_cure_mm": 2.9,
      "matrix_type": "methacrylate",
      "suitable_for_occlusal": true,
      "requires_capping": false,
      "category": "microhybrid",
      "region": "Asia",
      "manufacturer": "Shofu",
      "notes": "Японский производитель, популярен в Азии",
      "year_released": 2016,
      "price_rub": 3000
    },
    {
      "name": "Estelite Asteria",
      "viscosity": "high",
      "polymerization_shrinkage_percent": 2.0,
      "microhardness_KHN": 76.2,
      "filler_content_percent": 79,
      "wear_resistance": "very_high",
      "depth_of_cure_mm": 2.5,
      "matrix_type": "methacrylate",
      "suitable_for_occlusal": true,
      "requires_capping": false,
      "category": "nanocomposite",
      "region": "Asia",
      "manufacturer": "Tokuyama Dental",
      "notes": "Японский производитель, высококачественный нанокомпозит",
      "year_released": 2017,
      "price_rub": 3700
    },
    {
      "name": "Filtek Bulk Fill",
      "viscosity": "high",
      "polymerization_shrinkage_percent": 2.4,
      "microhardness_KHN": 70.3,
      "filler_content_percent": 76,
      "wear_resistance": "high",
      "depth_of_cure_mm": 4.5,
      "matrix_type": "methacrylate",
      "suitable_for_occlusal": true,
      "requires_capping": false,
      "category": "high_viscosity_bulk_fill",
      "region": "USA",
      "manufacturer": "3M ESPE",
      "notes": "Bulk fill композит, популярен в США",
      "year_released": 2013,
      "price_rub": 4100
    },
    {
      "name": "Tetric EvoCeram",
      "viscosity": "high",
      "polymerization_shrinkage_percent": 2.1,
      "microhardness_KHN": 71.5,
      "filler_content_percent": 74,
      "wear_resistance": "high",
      "depth_of_cure_mm": 2.8,
      "matrix_type": "methacrylate",
      "suitable_for_occlusal": true,
      "requires_capping": false,
      "category": "nanocomposite",
      "region": "international",
      "manufacturer": "Ivoclar Vivadent",
      "notes": "Универсальный нанокомпозит, популярен во всем мире",
      "year_released": 2014,
      "price_rub": 3900
    },
    {
      "name": "Venus Diamond",
      "viscosity": "high",
      "polymerization_shrinkage_percent": 2.5,
      "microhardness_KHN": 69.8,
      "filler_content_percent": 71,
      "wear_resistance": "high",
      "depth_of_cure_mm": 2.9,
      "matrix_type": "methacrylate",
      "suitable_for_occlusal": true,
      "requires_capping": false,
      "category": "microhybrid",
      "region": "international",
      "manufacturer": "Heraeus Kulzer",
      "notes": "Универсальный микрогибридный композит",
      "year_released": 2012,
      "price_rub": 3200
    },
    {
      "name": "Clearfil Majesty",
      "viscosity": "high",
      "polymerization_shrinkage_percent": 2.2,
      "microhardness_KHN": 74.6,
      "filler_content_percent": 78,
      "wear_resistance": "very_high",
      "depth_of_cure_mm": 2.6,
      "matrix_type": "methacrylate",
      "suitable_for_occlusal": true,
      "requires_capping": false,
      "category": "nanocomposite",
      "region": "Asia",
      "manufacturer": "Kuraray",
      "notes": "Японский производитель, высококачественный нанокомпозит",
      "year_released": 2013,
      "price_rub": 4400
    },
    {
      "name": "Ceram-X",
      "viscosity": "high",
      "polymerization_shrinkage_percent": 2.3,
      "microhardness_KHN": 67.5,
      "filler_content_percent": 69,
      "wear_resistance": "high",
      "depth_of_cure_mm": 3.1,
      "matrix_type": "methacrylate",
      "suitable_for_occlusal": true,
      "requires_capping": false,
      "category": "microhybrid",
      "region": "international",
      "manufacturer": "Dentsply Sirona",
      "notes": "Универсальный микрогибридный композит",
      "year_released": 2011,
      "price_rub": 3100
    },
    {
      "name": "Gradia Direct",
      "viscosity": "high",
      "polymerization_shrinkage_percent": 2.4,
      "microhardness_KHN": 66.8,
      "filler_content_percent": 70,
      "wear_resistance": "high",
      "depth_of_cure_mm": 3.0,
      "matrix_type": "methacrylate",
      "suitable_for_occlusal": true,
      "requires_capping": false,
      "category": "microhybrid",
      "region": "Asia",
      "manufacturer": "GC Corporation",
      "notes": "Японский производитель, популярен в Азии",
      "year_released": 2010,
      "price_rub": 2800
    },
    {
      "name": "Herculite XRV",
      "viscosity": "high",
      "polymerization_shrinkage_percent": 2.6,
      "microhardness_KHN": 68.2,
      "filler_content_percent": 72,
      "wear_resistance": "high",
      "depth_of_cure_mm": 2.9,
      "matrix_type": "methacrylate",
      "suitable_for_occlusal": true,
      "requires_capping": false,
      "category": "microhybrid",
      "region": "USA",
      "manufacturer": "Kerr",
      "notes": "Популярен в США, хорошее качество",
      "year_released": 2009,
      "price_rub": 2700
    },
    {
      "name": "Point 4",
      "viscosity": "high",
      "polymerization_shrinkage_percent": 2.5,
      "microhardness_KHN": 70.1,
      "filler_content_percent": 73,
      "wear_resistance": "high",
      "depth_of_cure_mm": 2.8,
      "matrix_type": "methacrylate",
      "suitable_for_occlusal": true,
      "requires_capping": false,
      "category": "microhybrid",
      "region": "USA",
      "manufacturer": "Kerr",
      "notes": "Популярен в США",
      "year_released": 2010,
      "price_rub": 2900
    },
    {
      "name": "Spectrum TPH",
      "viscosity": "high",
      "polymerization_shrinkage_percent": 2.7,
      "microhardness_KHN": 65.9,
      "filler_content_percent": 68,
      "wear_resistance": "high",
      "depth_of_cure_mm": 3.1,
      "matrix_type": "methacrylate",
      "suitable_for_occlusal": true,
      "requires_capping": false,
      "category": "microhybrid",
      "region": "international",
      "manufacturer": "Dentsply Sirona",
      "notes": "Универсальный композит",
      "year_released": 2011,
      "price_rub": 3000
    },
    {
      "name": "Filtek Z250",
      "viscosity": "high",
      "polymerization_shrinkage_percent": 2.8,
      "microhardness_KHN": 81.2,
      "filler_content_percent": 82,
      "wear_resistance": "very_high",
      "depth_of_cure_mm": 2.4,
      "matrix_type": "methacrylate",
      "suitable_for_occlusal": true,
      "requires_capping": false,
      "category": "microhybrid",
      "region": "USA",
      "manufacturer": "3M ESPE",
      "notes": "Классический композит, популярен в США, высокая прочность",
      "year_released": 2007,
      "price_rub": 3500
    },
    {
      "name": "Esthet-X HD",
      "viscosity": "high",
      "polymerization_shrinkage_percent": 2.4,
      "microhardness_KHN": 72.7,
      "filler_content_percent": 75,
      "wear_resistance": "high",
      "depth_of_cure_mm": 2.7,
      "matrix_type": "methacrylate",
      "suitable_for_occlusal": true,
      "requires_capping": false,
      "category": "nanocomposite",
      "region": "USA",
      "manufacturer": "Dentsply Sirona",
      "notes": "Высококачественный нанокомпозит, популярен в США",
      "year_released": 2012,
      "price_rub": 3600
    },
    {
      "name": "Omnichroma",
      "viscosity": "high",
      "polymerization_shrinkage_percent": 2.0,
      "microhardness_KHN": 73.5,
      "filler_content_percent": 76,
      "wear_resistance": "high",
      "depth_of_cure_mm": 2.6,
      "matrix_type": "methacrylate",
      "suitable_for_occlusal": true,
      "requires_capping": false,
      "category": "nanocomposite",
      "region": "international",
      "manufacturer": "Tokuyama Dental",
      "notes": "Универсальный оттенок, популярен во всем мире",
      "year_released": 2018,
      "price_rub": 5200
    },
    {
      "name": "IPS Empress Direct",
      "viscosity": "high",
      "polymerization_shrinkage_percent": 2.3,
      "microhardness_KHN": 70.9,
      "filler_content_percent": 73,
      "wear_resistance": "high",
      "depth_of_cure_mm": 2.8,
      "matrix_type": "methacrylate",
      "suitable_for_occlusal": true,
      "requires_capping": false,
      "category": "microhybrid",
      "region": "international",
      "manufacturer": "Ivoclar Vivadent",
      "notes": "Универсальный композит",
      "year_released": 2013,
      "price_rub": 4000
    },
    {
      "name": "Kalore",
      "viscosity": "high",
      "polymerization_shrinkage_percent": 1.8,
      "microhardness_KHN": 75.4,
      "filler_content_percent": 77,
      "wear_resistance": "very_high",
      "depth_of_cure_mm": 2.5,
      "matrix_type": "methacrylate",
      "suitable_for_occlusal": true,
      "requires_capping": false,
      "category": "nanocomposite",
      "region": "international",
      "manufacturer": "GC Corporation",
      "notes": "Низкая усадка, высокое качество",
      "year_released": 2015,
      "price_rub": 3800
    },
    {
      "name": "Beautifil II",
      "viscosity": "high",
      "polymerization_shrinkage_percent": 2.2,
      "microhardness_KHN": 69.3,
      "filler_content_percent": 71,
      "wear_resistance": "high",
      "depth_of_cure_mm": 2.9,
      "matrix_type": "methacrylate",
      "suitable_for_occlusal": true,
      "requires_capping": false,
      "category": "microhybrid",
      "region": "Asia",
      "manufacturer": "Shofu",
      "notes": "Популярен в Азии, хорошее качество",
      "year_released": 2014,
      "price_rub": 3400
    },
    {
      "name": "Estelite Beta",
      "viscosity": "high",
      "polymerization_shrinkage_percent": 2.1,
      "microhardness_KHN": 74.8,
      "filler_content_percent": 78,
      "wear_resistance": "very_high",
      "depth_of_cure_mm": 2.6,
      "matrix_type": "methacrylate",
      "suitable_for_occlusal": true,
      "requires_capping": false,
      "category": "nanocomposite",
      "region": "Asia",
      "manufacturer": "Tokuyama Dental",
      "notes": "Японский производитель, высококачественный",
      "year_released": 2015,
      "price_rub": 3500
    },
    {
      "name": "Gradia Direct Anterior",
      "viscosity": "high",
      "polymerization_shrinkage_percent": 2.3,
      "microhardness_KHN": 66.5,
      "filler_content_percent": 69,
      "wear_resistance": "high",
      "depth_of_cure_mm": 3.0,
      "matrix_type": "methacrylate",
      "suitable_for_occlusal": true,
      "requires_capping": false,
      "category": "microhybrid",
      "region": "Asia",
      "manufacturer": "GC Corporation",
      "notes": "Японский производитель",
      "year_released": 2010,
      "price_rub": 2800
    },
    {
      "name": "Clearfil AP-X",
      "viscosity": "high",
      "polymerization_shrinkage_percent": 2.4,
      "microhardness_KHN": 72.1,
      "filler_content_percent": 74,
      "wear_resistance": "high",
      "depth_of_cure_mm": 2.7,
      "matrix_type": "methacrylate",
      "suitable_for_occlusal": true,
      "requires_capping": false,
      "category": "nanocomposite",
      "region": "Asia",
      "manufacturer": "Kuraray",
      "notes": "Японский производитель, популярен в Азии",
      "year_released": 2012,
      "price_rub": 3300
    },
    {
      "name": "Zhermack Esthetic",
      "viscosity": "high",
      "polymerization_shrinkage_percent": 2.5,
      "microhardness_KHN": 68.7,
      "filler_content_percent": 70,
      "wear_resistance": "high",
      "depth_of_cure_mm": 3.0,
      "matrix_type": "methacrylate",
      "suitable_for_occlusal": true,
      "requires_capping": false,
      "category": "microhybrid",
      "region": "Italy",
      "manufacturer": "Zhermack",
      "notes": "Итальянский производитель, популярен в Италии",
      "year_released": 2016,
      "price_rub": 2400
    },
    {
      "name": "Micerium Evo",
      "viscosity": "high",
      "polymerization_shrinkage_percent": 2.2,
      "microhardness_KHN": 71.2,
      "filler_content_percent": 73,
      "wear_resistance": "high",
      "depth_of_cure_mm": 2.8,
      "matrix_type": "methacrylate",
      "suitable_for_occlusal": true,
      "requires_capping": false,
      "category": "microhybrid",
      "region": "Italy",
      "manufacturer": "Micerium",
      "notes": "Итальянский производитель",
      "year_released": 2017,
      "price_rub": 3600
    },
    {
      "name": "Филтек П60",
      "viscosity": "high",
      "polymerization_shrinkage_percent": 2.9,
      "microhardness_KHN": 80.5,
      "filler_content_percent": 83,
      "wear_resistance": "very_high",
      "depth_of_cure_mm": 2.3,
      "matrix_type": "methacrylate",
      "suitable_for_occlusal": true,
      "requires_capping": false,
      "category": "microhybrid",
      "region": "Russia",
      "manufacturer": "3M ESPE",
      "notes": "Популярен в России, высокая прочность для жевательных зубов",
      "year_released": 2006,
      "price_rub": 3200
    },
    {
      "name": "Филтек Z250",
      "viscosity": "high",
      "polymerization_shrinkage_percent": 2.8,
      "microhardness_KHN": 81.2,
      "filler_content_percent": 82,
      "wear_resistance": "very_high",
      "depth_of_cure_mm": 2.4,
      "matrix_type": "methacrylate",
      "suitable_for_occlusal": true,
      "requires_capping": false,
      "category": "microhybrid",
      "region": "Russia",
      "manufacturer": "3M ESPE",
      "notes": "Популярен в России",
      "year_released": 2007,
      "price_rub": 3500
    },
    {
      "name": "Charisma Diamond",
      "viscosity": "high",
      "polymerization_shrinkage_percent": 2.4,
      "microhardness_KHN": 70.8,
      "filler_content_percent": 72,
      "wear_resistance": "high",
      "depth_of_cure_mm": 2.9,
      "matrix_type": "methacrylate",
      "suitable_for_occlusal": true,
      "requires_capping": false,
      "category": "microhybrid",
      "region": "Russia",
      "manufacturer": "Heraeus Kulzer",
      "notes": "Популярен в России",
      "year_released": 2013,
      "price_rub": 3100
    },
    {
      "name": "Septodont Universal",
      "viscosity": "high",
      "polymerization_shrinkage_percent": 2.6,
      "microhardness_KHN": 69.8,
      "filler_content_percent": 71,
      "wear_resistance": "high",
      "depth_of_cure_mm": 2.9,
      "matrix_type": "methacrylate",
      "suitable_for_occlusal": true,
      "requires_capping": false,
      "category": "microhybrid",
      "region": "Europe",
      "manufacturer": "Septodont",
      "notes": "Французский производитель, популярен в Европе",
      "year_released": 2015,
      "price_rub": 2600
    },
    {
      "name": "Septodont Esthetic",
      "viscosity": "high",
      "polymerization_shrinkage_percent": 2.4,
      "microhardness_KHN": 71.5,
      "filler_content_percent": 73,
      "wear_resistance": "high",
      "depth_of_cure_mm": 2.8,
      "matrix_type": "methacrylate",
      "suitable_for_occlusal": true,
      "requires_capping": false,
      "category": "nanocomposite",
      "region": "Europe",
      "manufacturer": "Septodont",
      "notes": "Французский производитель, высокоэстетичный нанокомпозит",
      "year_released": 2015,
      "price_rub": 2700
    },
    {
      "name": "COLTENE Brilliant",
      "viscosity": "high",
      "polymerization_shrinkage_percent": 2.3,
      "microhardness_KHN": 70.2,
      "filler_content_percent": 72,
      "wear_resistance": "high",
      "depth_of_cure_mm": 2.9,
      "matrix_type": "methacrylate",
      "suitable_for_occlusal": true,
      "requires_capping": false,
      "category": "microhybrid",
      "region": "Europe",
      "manufacturer": "COLTENE",
      "notes": "Швейцарский производитель, популярен в Европе",
      "year_released": 2014,
      "price_rub": 2800
    },
    {
      "name": "COLTENE Brilliant EverGlow",
      "viscosity": "high",
      "polymerization_shrinkage_percent": 2.2,
      "microhardness_KHN": 72.8,
      "filler_content_percent": 75,
      "wear_resistance": "high",
      "depth_of_cure_mm": 2.7,
      "matrix_type": "methacrylate",
      "suitable_for_occlusal": true,
      "requires_capping": false,
      "category": "nanocomposite",
      "region": "Europe",
      "manufacturer": "COLTENE",
      "notes": "Швейцарский производитель, нанокомпозит",
      "year_released": 2016,
      "price_rub": 3000
    },
    {
      "name": "Bredent Brilliant",
      "viscosity": "high",
      "polymerization_shrinkage_percent": 2.5,
      "microhardness_KHN": 68.5,
      "filler_content_percent": 70,
      "wear_resistance": "high",
      "depth_of_cure_mm": 3.0,
      "matrix_type": "methacrylate",
      "suitable_for_occlusal": true,
      "requires_capping": false,
      "category": "microhybrid",
      "region": "Europe",
      "manufacturer": "Bredent",
      "notes": "Немецкий производитель, популярен в Германии и Европе",
      "year_released": 2015,
      "price_rub": 2900
    },
    {
      "name": "MEGADENTA Universal",
      "viscosity": "high",
      "polymerization_shrinkage_percent": 2.6,
      "microhardness_KHN": 67.9,
      "filler_content_percent": 69,
      "wear_resistance": "high",
      "depth_of_cure_mm": 3.1,
      "matrix_type": "methacrylate",
      "suitable_for_occlusal": true,
      "requires_capping": false,
      "category": "microhybrid",
      "region": "Europe",
      "manufacturer": "MEGADENTA",
      "notes": "Немецкий производитель, популярен в Европе",
      "year_released": 2016,
      "price_rub": 2500
    },
    {
      "name": "Voco GrandioSO Heavy",
      "viscosity": "high",
      "polymerization_shrinkage_percent": 2.0,
      "microhardness_KHN": 75.3,
      "filler_content_percent": 78,
      "wear_resistance": "very_high",
      "depth_of_cure_mm": 2.5,
      "matrix_type": "methacrylate",
      "suitable_for_occlusal": true,
      "requires_capping": false,
      "category": "nanocomposite",
      "region": "Europe",
      "manufacturer": "Voco",
      "notes": "Немецкий производитель, высокая прочность для жевательных зубов",
      "year_released": 2014,
      "price_rub": 3700
    },
    {
      "name": "Voco Solitaire 2",
      "viscosity": "high",
      "polymerization_shrinkage_percent": 2.3,
      "microhardness_KHN": 71.8,
      "filler_content_percent": 74,
      "wear_resistance": "high",
      "depth_of_cure_mm": 2.8,
      "matrix_type": "methacrylate",
      "suitable_for_occlusal": true,
      "requires_capping": false,
      "category": "nanocomposite",
      "region": "Europe",
      "manufacturer": "Voco",
      "notes": "Немецкий производитель, нанокомпозит",
      "year_released": 2015,
      "price_rub": 3500
    },
    {
      "name": "Ivoclar Tetric EvoFlow",
      "viscosity": "low",
      "polymerization_shrinkage_percent": 3.2,
      "microhardness_KHN": 35.5,
      "filler_content_percent": 58,
      "wear_resistance": "low",
      "depth_of_cure_mm": 4.0,
      "matrix_type": "methacrylate",
      "suitable_for_occlusal": false,
      "requires_capping": true,
      "category": "low_viscosity_bulk_fill",
      "region": "Europe",
      "manufacturer": "Ivoclar Vivadent",
      "notes": "Швейцарский производитель, flowable композит, требует покрытия",
      "year_released": 2015,
      "price_rub": 3000
    },
    {
      "name": "Ivoclar Tetric PowerFill",
      "viscosity": "high",
      "polymerization_shrinkage_percent": 1.9,
      "microhardness_KHN": 76.5,
      "filler_content_percent": 80,
      "wear_resistance": "very_high",
      "depth_of_cure_mm": 4.5,
      "matrix_type": "methacrylate",
      "suitable_for_occlusal": true,
      "requires_capping": false,
      "category": "high_viscosity_bulk_fill",
      "region": "Europe",
      "manufacturer": "Ivoclar Vivadent",
      "notes": "Швейцарский производитель, bulk fill композит, очень низкая усадка",
      "year_released": 2018,
      "price_rub": 4600
    },
    {
      "name": "Ivoclar Tetric EvoCeram Bulk Fill",
      "viscosity": "high",
      "polymerization_shrinkage_percent": 2.1,
      "microhardness_KHN": 73.2,
      "filler_content_percent": 76,
      "wear_resistance": "high",
      "depth_of_cure_mm": 4.5,
      "matrix_type": "methacrylate",
      "suitable_for_occlusal": true,
      "requires_capping": false,
      "category": "high_viscosity_bulk_fill",
      "region": "Europe",
      "manufacturer": "Ivoclar Vivadent",
      "notes": "Швейцарский производитель, bulk fill композит",
      "year_released": 2014,
      "price_rub": 3900
    },
    {
      "name": "Heraeus Kulzer Venus",
      "viscosity": "high",
      "polymerization_shrinkage_percent": 2.5,
      "microhardness_KHN": 69.8,
      "filler_content_percent": 71,
      "wear_resistance": "high",
      "depth_of_cure_mm": 2.9,
      "matrix_type": "methacrylate",
      "suitable_for_occlusal": true,
      "requires_capping": false,
      "category": "microhybrid",
      "region": "Europe",
      "manufacturer": "Heraeus Kulzer",
      "notes": "Немецкий производитель, популярен в Европе",
      "year_released": 2011,
      "price_rub": 3100
    },
    {
      "name": "Heraeus Kulzer Venus Pearl",
      "viscosity": "high",
      "polymerization_shrinkage_percent": 2.4,
      "microhardness_KHN": 72.1,
      "filler_content_percent": 74,
      "wear_resistance": "high",
      "depth_of_cure_mm": 2.8,
      "matrix_type": "methacrylate",
      "suitable_for_occlusal": true,
      "requires_capping": false,
      "category": "nanocomposite",
      "region": "Europe",
      "manufacturer": "Heraeus Kulzer",
      "notes": "Немецкий производитель, нанокомпозит",
      "year_released": 2013,
      "price_rub": 3300
    },
    {
      "name": "Dentsply Sirona Ceram-X",
      "viscosity": "high",
      "polymerization_shrinkage_percent": 2.3,
      "microhardness_KHN": 67.5,
      "filler_content_percent": 69,
      "wear_resistance": "high",
      "depth_of_cure_mm": 3.1,
      "matrix_type": "methacrylate",
      "suitable_for_occlusal": true,
      "requires_capping": false,
      "category": "microhybrid",
      "region": "Europe",
      "manufacturer": "Dentsply Sirona",
      "notes": "Популярен в Европе, универсальный композит",
      "year_released": 2011,
      "price_rub": 3100
    },
    {
      "name": "Dentsply Sirona SDR flow+",
      "viscosity": "low",
      "polymerization_shrinkage_percent": 3.5,
      "microhardness_KHN": 32.8,
      "filler_content_percent": 52,
      "wear_resistance": "low",
      "depth_of_cure_mm": 4.5,
      "matrix_type": "methacrylate",
      "suitable_for_occlusal": false,
      "requires_capping": true,
      "category": "low_viscosity_bulk_fill",
      "region": "Europe",
      "manufacturer": "Dentsply Sirona",
      "notes": "Flowable композит, требует покрытия",
      "year_released": 2015,
      "price_rub": 3000
    },
    {
      "name": "Kerr OptiShade",
      "viscosity": "high",
      "polymerization_shrinkage_percent": 2.5,
      "microhardness_KHN": 70.5,
      "filler_content_percent": 72,
      "wear_resistance": "high",
      "depth_of_cure_mm": 2.9,
      "matrix_type": "methacrylate",
      "suitable_for_occlusal": true,
      "requires_capping": false,
      "category": "microhybrid",
      "region": "Europe",
      "manufacturer": "Kerr",
      "notes": "Популярен в Европе",
      "year_released": 2012,
      "price_rub": 3200
    },
    {
      "name": "Kerr Premise",
      "viscosity": "high",
      "polymerization_shrinkage_percent": 2.4,
      "microhardness_KHN": 71.2,
      "filler_content_percent": 73,
      "wear_resistance": "high",
      "depth_of_cure_mm": 2.8,
      "matrix_type": "methacrylate",
      "suitable_for_occlusal": true,
      "requires_capping": false,
      "category": "nanocomposite",
      "region": "Europe",
      "manufacturer": "Kerr",
      "notes": "Нанокомпозит, популярен в Европе",
      "year_released": 2011,
      "price_rub": 3100
    },
    {
      "name": "3M ESPE Filtek One Bulk Fill",
      "viscosity": "high",
      "polymerization_shrinkage_percent": 2.1,
      "microhardness_KHN": 74.8,
      "filler_content_percent": 77,
      "wear_resistance": "very_high",
      "depth_of_cure_mm": 4.5,
      "matrix_type": "methacrylate",
      "suitable_for_occlusal": true,
      "requires_capping": false,
      "category": "high_viscosity_bulk_fill",
      "region": "Europe",
      "manufacturer": "3M ESPE",
      "notes": "Bulk fill композит, популярен в Европе, очень низкая усадка",
      "year_released": 2016,
      "price_rub": 4300
    },
    {
      "name": "3M ESPE Filtek Universal",
      "viscosity": "high",
      "polymerization_shrinkage_percent": 2.6,
      "microhardness_KHN": 73.5,
      "filler_content_percent": 75,
      "wear_resistance": "high",
      "depth_of_cure_mm": 2.7,
      "matrix_type": "methacrylate",
      "suitable_for_occlusal": true,
      "requires_capping": false,
      "category": "nanocomposite",
      "region": "Europe",
      "manufacturer": "3M ESPE",
      "notes": "Универсальный нанокомпозит, популярен в Европе",
      "year_released": 2017,
      "price_rub": 4500
    },
    {
      "name": "Ultradent Opallis",
      "viscosity": "high",
      "polymerization_shrinkage_percent": 2.5,
      "microhardness_KHN": 68.9,
      "filler_content_percent": 70,
      "wear_resistance": "high",
      "depth_of_cure_mm": 3.0,
      "matrix_type": "methacrylate",
      "suitable_for_occlusal": true,
      "requires_capping": false,
      "category": "microhybrid",
      "region": "Europe",
      "manufacturer": "Ultradent",
      "notes": "Популярен в Европе",
      "year_released": 2013,
      "price_rub": 3400
    },
    {
      "name": "Ultradent Valiant",
      "viscosity": "high",
      "polymerization_shrinkage_percent": 2.3,
      "microhardness_KHN": 70.8,
      "filler_content_percent": 72,
      "wear_resistance": "high",
      "depth_of_cure_mm": 2.9,
      "matrix_type": "methacrylate",
      "suitable_for_occlusal": true,
      "requires_capping": false,
      "category": "microhybrid",
      "region": "Europe",
      "manufacturer": "Ultradent",
      "notes": "Популярен в Европе",
      "year_released": 2014,
      "price_rub": 3500
    },
    {
      "name": "DMG LuxaCore",
      "viscosity": "high",
      "polymerization_shrinkage_percent": 2.4,
      "microhardness_KHN": 69.5,
      "filler_content_percent": 71,
      "wear_resistance": "high",
      "depth_of_cure_mm": 2.9,
      "matrix_type": "methacrylate",
      "suitable_for_occlusal": true,
      "requires_capping": false,
      "category": "microhybrid",
      "region": "Europe",
      "manufacturer": "DMG",
      "notes": "Немецкий производитель, популярен в Европе",
      "year_released": 2012,
      "price_rub": 3200
    },
    {
      "name": "DMG LuxaCore Z",
      "viscosity": "high",
      "polymerization_shrinkage_percent": 2.2,
      "microhardness_KHN": 72.4,
      "filler_content_percent": 74,
      "wear_resistance": "high",
      "depth_of_cure_mm": 2.8,
      "matrix_type": "methacrylate",
      "suitable_for_occlusal": true,
      "requires_capping": false,
      "category": "nanocomposite",
      "region": "Europe",
      "manufacturer": "DMG",
      "notes": "Немецкий производитель, нанокомпозит",
      "year_released": 2014,
      "price_rub": 3400
    },
    {
      "name": "Schütz Dental Brilliant EverGlow",
      "viscosity": "high",
      "polymerization_shrinkage_percent": 2.5,
      "microhardness_KHN": 68.2,
      "filler_content_percent": 70,
      "wear_resistance": "high",
      "depth_of_cure_mm": 3.0,
      "matrix_type": "methacrylate",
      "suitable_for_occlusal": true,
      "requires_capping": false,
      "category": "microhybrid",
      "region": "Europe",
      "manufacturer": "Schütz Dental",
      "notes": "Немецкий производитель",
      "year_released": 2016,
      "price_rub": 3000
    },
    {
      "name": "Schütz Dental Brilliant NG",
      "viscosity": "high",
      "polymerization_shrinkage_percent": 2.3,
      "microhardness_KHN": 71.6,
      "filler_content_percent": 73,
      "wear_resistance": "high",
      "depth_of_cure_mm": 2.8,
      "matrix_type": "methacrylate",
      "suitable_for_occlusal": true,
      "requires_capping": false,
      "category": "nanocomposite",
      "region": "Europe",
      "manufacturer": "Schütz Dental",
      "notes": "Немецкий производитель, нанокомпозит",
      "year_released": 2017,
      "price_rub": 3100
    },
    {
      "name": "Kulzer Venus Bulk Fill",
      "viscosity": "high",
      "polymerization_shrinkage_percent": 2.0,
      "microhardness_KHN": 73.8,
      "filler_content_percent": 76,
      "wear_resistance": "very_high",
      "depth_of_cure_mm": 4.5,
      "matrix_type": "methacrylate",
      "suitable_for_occlusal": true,
      "requires_capping": false,
      "category": "high_viscosity_bulk_fill",
      "region": "Europe",
      "manufacturer": "Heraeus Kulzer",
      "notes": "Немецкий производитель, bulk fill композит",
      "year_released": 2014,
      "price_rub": 3600
    },
    {
      "name": "Kulzer Venus Diamond",
      "viscosity": "high",
      "polymerization_shrinkage_percent": 2.5,
      "microhardness_KHN": 69.8,
      "filler_content_percent": 71,
      "wear_resistance": "high",
      "depth_of_cure_mm": 2.9,
      "matrix_type": "methacrylate",
      "suitable_for_occlusal": true,
      "requires_capping": false,
      "category": "microhybrid",
      "region": "Europe",
      "manufacturer": "Heraeus Kulzer",
      "notes": "Немецкий производитель, популярен в Европе",
      "year_released": 2012,
      "price_rub": 3200
    },
    {
      "name": "Voco Admira Fusion",
      "viscosity": "high",
      "polymerization_shrinkage_percent": 1.8,
      "microhardness_KHN": 74.2,
      "filler_content_percent": 77,
      "wear_resistance": "very_high",
      "depth_of_cure_mm": 2.6,
      "matrix_type": "ormocer",
      "suitable_for_occlusal": true,
      "requires_capping": false,
      "category": "nanocomposite",
      "region": "Europe",
      "manufacturer": "Voco",
      "notes": "Немецкий производитель, Ormocer матрица, очень низкая усадка",
      "year_released": 2016,
      "price_rub": 3800
    },
    {
      "name": "Voco Admira Fusion Xtra",
      "viscosity": "high",
      "polymerization_shrinkage_percent": 1.5,
      "microhardness_KHN": 37.36,
      "filler_content_percent": 65,
      "wear_resistance": "medium",
      "depth_of_cure_mm": 4.5,
      "matrix_type": "ormocer",
      "suitable_for_occlusal": false,
      "requires_capping": true,
      "category": "high_viscosity_bulk_fill",
      "region": "Europe",
      "manufacturer": "Voco",
      "notes": "Немецкий производитель, Ormocer матрица, bulk fill",
      "year_released": 2015,
      "price_rub": 3000
    },
    {
      "name": "Ivoclar Heliomolar",
      "viscosity": "high",
      "polymerization_shrinkage_percent": 2.7,
      "microhardness_KHN": 68.5,
      "filler_content_percent": 70,
      "wear_resistance": "high",
      "depth_of_cure_mm": 3.0,
      "matrix_type": "methacrylate",
      "suitable_for_occlusal": true,
      "requires_capping": false,
      "category": "microhybrid",
      "region": "Europe",
      "manufacturer": "Ivoclar Vivadent",
      "notes": "Швейцарский производитель, классический композит",
      "year_released": 2010,
      "price_rub": 3000
    },
    {
      "name": "Ivoclar Tetric N-Ceram",
      "viscosity": "high",
      "polymerization_shrinkage_percent": 2.2,
      "microhardness_KHN": 72.8,
      "filler_content_percent": 75,
      "wear_resistance": "high",
      "depth_of_cure_mm": 2.8,
      "matrix_type": "methacrylate",
      "suitable_for_occlusal": true,
      "requires_capping": false,
      "category": "nanocomposite",
      "region": "Europe",
      "manufacturer": "Ivoclar Vivadent",
      "notes": "Швейцарский производитель, нанокомпозит",
      "year_released": 2015,
      "price_rub": 3700
    },
    {
      "name": "Ivoclar Tetric EvoFlow Bulk Fill",
      "viscosity": "low",
      "polymerization_shrinkage_percent": 3.8,
      "microhardness_KHN": 34.2,
      "filler_content_percent": 56,
      "wear_resistance": "low",
      "depth_of_cure_mm": 4.5,
      "matrix_type": "methacrylate",
      "suitable_for_occlusal": false,
      "requires_capping": true,
      "category": "low_viscosity_bulk_fill",
      "region": "Europe",
      "manufacturer": "Ivoclar Vivadent",
      "notes": "Швейцарский производитель, flowable bulk fill, требует покрытия",
      "year_released": 2015,
      "price_rub": 3000
    },
    {
      "name": "Dentsply Sirona Prime&Bond Universal",
      "viscosity": "high",
      "polymerization_shrinkage_percent": 2.4,
      "microhardness_KHN": 70.5,
      "filler_content_percent": 72,
      "wear_resistance": "high",
      "depth_of_cure_mm": 2.9,
      "matrix_type": "methacrylate",
      "suitable_for_occlusal": true,
      "requires_capping": false,
      "category": "microhybrid",
      "region": "Europe",
      "manufacturer": "Dentsply Sirona",
      "notes": "Популярен в Европе",
      "year_released": 2016,
      "price_rub": 3600
    },
    {
      "name": "Dentsply Sirona SureFil SDR",
      "viscosity": "low",
      "polymerization_shrinkage_percent": 4.2,
      "microhardness_KHN": 31.5,
      "filler_content_percent": 48,
      "wear_resistance": "low",
      "depth_of_cure_mm": 4.5,
      "matrix_type": "methacrylate",
      "suitable_for_occlusal": false,
      "requires_capping": true,
      "category": "low_viscosity_bulk_fill",
      "region": "Europe",
      "manufacturer": "Dentsply Sirona",
      "notes": "Flowable композит, требует покрытия",
      "year_released": 2015,
      "price_rub": 3000
    },
    {
      "name": "Kerr Nexus",
      "viscosity": "high",
      "polymerization_shrinkage_percent": 2.6,
      "microhardness_KHN": 69.2,
      "filler_content_percent": 71,
      "wear_resistance": "high",
      "depth_of_cure_mm": 2.9,
      "matrix_type": "methacrylate",
      "suitable_for_occlusal": true,
      "requires_capping": false,
      "category": "microhybrid",
      "region": "Europe",
      "manufacturer": "Kerr",
      "notes": "Популярен в Европе",
      "year_released": 2011,
      "price_rub": 3100
    },
    {
      "name": "Kerr Filtek Supreme",
      "viscosity": "high",
      "polymerization_shrinkage_percent": 2.7,
      "microhardness_KHN": 71.5,
      "filler_content_percent": 73,
      "wear_resistance": "high",
      "depth_of_cure_mm": 2.8,
      "matrix_type": "methacrylate",
      "suitable_for_occlusal": true,
      "requires_capping": false,
      "category": "nanocomposite",
      "region": "Europe",
      "manufacturer": "Kerr",
      "notes": "Нанокомпозит, популярен в Европе",
      "year_released": 2012,
      "price_rub": 3200
    },
    {
      "name": "3M ESPE Filtek P60",
      "viscosity": "high",
      "polymerization_shrinkage_percent": 2.9,
      "microhardness_KHN": 80.5,
      "filler_content_percent": 83,
      "wear_resistance": "very_high",
      "depth_of_cure_mm": 2.3,
      "matrix_type": "methacrylate",
      "suitable_for_occlusal": true,
      "requires_capping": false,
      "category": "microhybrid",
      "region": "Europe",
      "manufacturer": "3M ESPE",
      "notes": "Высокая прочность для жевательных зубов, популярен в Европе",
      "year_released": 2006,
      "price_rub": 3200
    },
    {
      "name": "3M ESPE Filtek Z250 XT",
      "viscosity": "high",
      "polymerization_shrinkage_percent": 2.8,
      "microhardness_KHN": 81.2,
      "filler_content_percent": 82,
      "wear_resistance": "very_high",
      "depth_of_cure_mm": 2.4,
      "matrix_type": "methacrylate",
      "suitable_for_occlusal": true,
      "requires_capping": false,
      "category": "microhybrid",
      "region": "Europe",
      "manufacturer": "3M ESPE",
      "notes": "Классический композит, популярен в Европе",
      "year_released": 2007,
      "price_rub": 3500
    },
    {
      "name": "Ultradent Opallis Bulk Fill",
      "viscosity": "high",
      "polymerization_shrinkage_percent": 2.2,
      "microhardness_KHN": 72.3,
      "filler_content_percent": 75,
      "wear_resistance": "high",
      "depth_of_cure_mm": 4.5,
      "matrix_type": "methacrylate",
      "suitable_for_occlusal": true,
      "requires_capping": false,
      "category": "high_viscosity_bulk_fill",
      "region": "Europe",
      "manufacturer": "Ultradent",
      "notes": "Bulk fill композит, популярен в Европе",
      "year_released": 2015,
      "price_rub": 3500
    },
    {
      "name": "DMG LuxaCore Dual",
      "viscosity": "high",
      "polymerization_shrinkage_percent": 2.3,
      "microhardness_KHN": 70.9,
      "filler_content_percent": 72,
      "wear_resistance": "high",
      "depth_of_cure_mm": 2.9,
      "matrix_type": "methacrylate",
      "suitable_for_occlusal": true,
      "requires_capping": false,
      "category": "microhybrid",
      "region": "Europe",
      "manufacturer": "DMG",
      "notes": "Немецкий производитель, dual-cure",
      "year_released": 2015,
      "price_rub": 3400
    },
    {
      "name": "Schütz Dental Brilliant Universal",
      "viscosity": "high",
      "polymerization_shrinkage_percent": 2.4,
      "microhardness_KHN": 70.1,
      "filler_content_percent": 71,
      "wear_resistance": "high",
      "depth_of_cure_mm": 2.9,
      "matrix_type": "methacrylate",
      "suitable_for_occlusal": true,
      "requires_capping": false,
      "category": "microhybrid",
      "region": "Europe",
      "manufacturer": "Schütz Dental",
      "notes": "Немецкий производитель, универсальный композит",
      "year_released": 2016,
      "price_rub": 3000
    },
    {
      "name": "TBF Optimal",
      "viscosity": "high",
      "polymerization_shrinkage_percent": 2.0,
      "microhardness_KHN": 55.0,
      "filler_content_percent": 40,
      "wear_resistance": "high",
      "depth_of_cure_mm": 4.5,
      "matrix_type": "methacrylate",
      "suitable_for_occlusal": true,
      "requires_capping": false,
      "category": "high_viscosity_bulk_fill",
      "region": "international",
      "manufacturer": "Ivoclar Vivadent",
      "notes": "Оптимальный композит с наполнителем 40% (в диапазоне 25-50%)",
      "year_released": 2013,
      "price_rub": 3800
    },
    {
      "name": "FBP Optimal",
      "viscosity": "high",
      "polymerization_shrinkage_percent": 2.2,
      "microhardness_KHN": 52.0,
      "filler_content_percent": 35,
      "wear_resistance": "high",
      "depth_of_cure_mm": 4.5,
      "matrix_type": "methacrylate",
      "suitable_for_occlusal": true,
      "requires_capping": false,
      "category": "high_viscosity_bulk_fill",
      "region": "international",
      "manufacturer": "3M ESPE",
      "notes": "Оптимальный композит с наполнителем 35% (в диапазоне 25-50%)",
      "year_released": 2013,
      "price_rub": 4200
    },
    {
      "name": "Estelite Sigma Quick OPA",
      "viscosity": "high",
      "polymerization_shrinkage_percent": 2.2,
      "microhardness_KHN": 72.5,
      "filler_content_percent": 45,
      "wear_resistance": "high",
      "depth_of_cure_mm": 2.7,
      "matrix_type": "methacrylate",
      "suitable_for_occlusal": true,
      "requires_capping": false,
      "category": "nanocomposite",
      "region": "Asia",
      "manufacturer": "Tokuyama Dental",
      "notes": "Estelite Sigma Quick OPA (Opaque) - розовая упаковка, оптимальный наполнитель 45%",
      "year_released": 2014,
      "price_rub": 3200
    },
    {
      "name": "Estelite Sigma Quick O",
      "viscosity": "high",
      "polymerization_shrinkage_percent": 2.3,
      "microhardness_KHN": 71.2,
      "filler_content_percent": 42,
      "wear_resistance": "high",
      "depth_of_cure_mm": 2.7,
      "matrix_type": "methacrylate",
      "suitable_for_occlusal": true,
      "requires_capping": false,
      "category": "nanocomposite",
      "region": "Asia",
      "manufacturer": "Tokuyama Dental",
      "notes": "Estelite Sigma Quick O (Opaque) - розовая упаковка, оптимальный наполнитель 42%",
      "year_released": 2014,
      "price_rub": 3150
    },
    {
      "name": "Estelite Sigma Quick OA3",
      "viscosity": "high",
      "polymerization_shrinkage_percent": 2.25,
      "microhardness_KHN": 72.0,
      "filler_content_percent": 44,
      "wear_resistance": "high",
      "depth_of_cure_mm": 2.7,
      "matrix_type": "methacrylate",
      "suitable_for_occlusal": true,
      "requires_capping": false,
      "category": "nanocomposite",
      "region": "Asia",
      "manufacturer": "Tokuyama Dental",
      "notes": "Estelite Sigma Quick OA3 (Opaque A3) - розовая упаковка, оптимальный наполнитель 44%",
      "year_released": 2014,
      "price_rub": 3250
    },
    {
      "name": "Estelite Sigma Quick A2",
      "viscosity": "high",
      "polymerization_shrinkage_percent": 2.3,
      "microhardness_KHN": 71.8,
      "filler_content_percent": 43,
      "wear_resistance": "high",
      "depth_of_cure_mm": 2.7,
      "matrix_type": "methacrylate",
      "suitable_for_occlusal": true,
      "requires_capping": false,
      "category": "nanocomposite",
      "region": "Asia",
      "manufacturer": "Tokuyama Dental",
      "notes": "Estelite Sigma Quick A2 - розовая упаковка, оптимальный наполнитель 43%",
      "year_released": 2014,
      "price_rub": 3100
    },
    {
      "name": "Estelite Universal",
      "viscosity": "high",
      "polymerization_shrinkage_percent": 2.1,
      "microhardness_KHN": 73.5,
      "filler_content_percent": 48,
      "wear_resistance": "very_high",
      "depth_of_cure_mm": 2.6,
      "matrix_type": "methacrylate",
      "suitable_for_occlusal": true,
      "requires_capping": false,
      "category": "nanocomposite",
      "region": "Asia",
      "manufacturer": "Tokuyama Dental",
      "notes": "Estelite Universal - белая упаковка с красным, оптимальный наполнитель 48%",
      "year_released": 2016,
      "price_rub": 3400
    },
    {
      "name": "Estelite Color Ochre",
      "viscosity": "high",
      "polymerization_shrinkage_percent": 2.4,
      "microhardness_KHN": 70.5,
      "filler_content_percent": 46,
      "wear_resistance": "high",
      "depth_of_cure_mm": 2.5,
      "matrix_type": "methacrylate",
      "suitable_for_occlusal": true,
      "requires_capping": false,
      "category": "nanocomposite",
      "region": "Asia",
      "manufacturer": "Tokuyama Dental",
      "notes": "Estelite Color Ochre (желтый) - оптимальный наполнитель 46%",
      "year_released": 2015,
      "price_rub": 3300
    },
    {
      "name": "Estelite Color Clear",
      "viscosity": "high",
      "polymerization_shrinkage_percent": 2.35,
      "microhardness_KHN": 71.0,
      "filler_content_percent": 47,
      "wear_resistance": "high",
      "depth_of_cure_mm": 2.6,
      "matrix_type": "methacrylate",
      "suitable_for_occlusal": true,
      "requires_capping": false,
      "category": "nanocomposite",
      "region": "Asia",
      "manufacturer": "Tokuyama Dental",
      "notes": "Estelite Color Clear (синий/прозрачный) - оптимальный наполнитель 47%",
      "year_released": 2015,
      "price_rub": 3350
    },
    {
      "name": "Estelite Flow Quick",
      "viscosity": "low",
      "polymerization_shrinkage_percent": 2.5,
      "microhardness_KHN": 65.8,
      "filler_content_percent": 40,
      "wear_resistance": "medium",
      "depth_of_cure_mm": 3.5,
      "matrix_type": "methacrylate",
      "suitable_for_occlusal": false,
      "requires_capping": true,
      "category": "low_viscosity",
      "region": "Asia",
      "manufacturer": "Tokuyama Dental",
      "notes": "Estelite Flow Quick - flowable версия, оптимальный наполнитель 40%",
      "year_released": 2015,
      "price_rub": 2900
    },
    {
      "name": "Estelite Posterior",
      "viscosity": "high",
      "polymerization_shrinkage_percent": 2.0,
      "microhardness_KHN": 75.2,
      "filler_content_percent": 49,
      "wear_resistance": "very_high",
      "depth_of_cure_mm": 2.8,
      "matrix_type": "methacrylate",
      "suitable_for_occlusal": true,
      "requires_capping": false,
      "category": "nanocomposite",
      "region": "Asia",
      "manufacturer": "Tokuyama Dental",
      "notes": "Estelite Posterior - для жевательных зубов, оптимальный наполнитель 49%",
      "year_released": 2017,
      "price_rub": 3600
    },
    {
      "name": "Estelite LV",
      "viscosity": "low",
      "polymerization_shrinkage_percent": 2.6,
      "microhardness_KHN": 64.5,
      "filler_content_percent": 38,
      "wear_resistance": "medium",
      "depth_of_cure_mm": 3.8,
      "matrix_type": "methacrylate",
      "suitable_for_occlusal": false,
      "requires_capping": true,
      "category": "low_viscosity",
      "region": "Asia",
      "manufacturer": "Tokuyama Dental",
      "notes": "Estelite LV (Low Viscosity) - низкая вязкость, оптимальный наполнитель 38%",
      "year_released": 2016,
      "price_rub": 2800
    },
    {
      "name": "Estelite Palfique",
      "viscosity": "high",
      "polymerization_shrinkage_percent": 2.15,
      "microhardness_KHN": 74.0,
      "filler_content_percent": 50,
      "wear_resistance": "very_high",
      "depth_of_cure_mm": 2.7,
      "matrix_type": "methacrylate",
      "suitable_for_occlusal": true,
      "requires_capping": false,
      "category": "nanocomposite",
      "region": "Asia",
      "manufacturer": "Tokuyama Dental",
      "notes": "Estelite Palfique - премиум линейка, оптимальный наполнитель 50%",
      "year_released": 2018,
      "price_rub": 3800
    }
  ],
  "selection_criteria": {
    "for_occlusal_restorations": {
      "required": {
        "viscosity": "high",
        "polymerization_shrinkage_percent_max": 3.0,
        "microhardness_KHN_min": 50,
        "suitable_for_occlusal": true,
        "requires_capping": false
      },
      "preferred": {
        "microhardness_KHN_min": 70,
        "filler_content_percent_range": [
          25,
          50
        ],
        "wear_resistance": "high",
        "depth_of_cure_mm_min": 4.5
      },
      "excluded_categories": [
        "low_viscosity_bulk_fill"
      ]
    },
    "for_patients_with_occlusion_anomalies": {
      "additional_requirements": {
        "wear_resistance": "high",
        "microhardness_KHN_min": 60,
        "polymerization_shrinkage_percent_max": 2.5
      }
    }
  },
  "emg_based_classification": {
    "wear_severity_none_mild": {
      "mvc_hyperfunction_percent": ">20",
      "mvc_duration_sec_per_min": "1-2",
      "recommended_microhardness_min": 50
    },
    "wear_severity_moderate_severe": {
      "mvc_hyperfunction_percent": ">20",
      "mvc_duration_sec_per_min": "4-6",
      "recommended_microhardness_min": 70,
      "recommended_wear_resistance": "very_high"
    }
  },
  "twes2_classification": {
    "description": "Tooth Wear Evaluation System 2.0 (TWES 2.0) - современная классификация патологической стираемости зубов",
    "source": "Wetselaar et al. 2020, Journal of Oral Rehabilitation",
    "url": "https://pmc.ncbi.nlm.nih.gov/articles/PMC7384115/",
    "grades": {
      "0": {
        "name": "Grade 0",
        "description": "Не наблюдается стирания",
        "depth": "Нет стирания",
        "tissues": "Эмаль не затронута",
        "characteristics": "Отсутствие видимого стирания зубов",
        "clinical_significance": "Физиологическая норма, симптомов нет",
        "recommended_microhardness_min": 50,
        "recommended_wear_resistance": "high",
        "recommended_filler_min": 60,
        "notes": "Нормальное состояние, профилактические композиты"
      },
      "1": {
        "name": "Grade 1",
        "description": "Стирание в пределах эмали",
        "depth": "В пределах эмали",
        "tissues": "Эмаль",
        "characteristics": "Стирание в пределах эмали, сглаживание бугров и режущих краёв, дентин не обнажён",
        "clinical_significance": "Начальная стадия, часто бессимптомна, функциональная перегрузка",
        "recommended_microhardness_min": 50,
        "recommended_wear_resistance": "high",
        "recommended_filler_min": 60,
        "notes": "Начальная стадия, композиты с хорошей износостойкостью"
      },
      "2": {
        "name": "Grade 2",
        "description": "Лёгкая степень - до 1/3 коронки",
        "depth": "До ≤ 1/3 коронки",
        "tissues": "Эмаль + дентин",
        "characteristics": "Стирание эмали, обнажение дентина, потеря высоты коронки до ≤ 1/3",
        "clinical_significance": "Повышенная чувствительность, изменение высоты бугров, начальное снижение высоты прикуса",
        "recommended_microhardness_min": 60,
        "recommended_wear_resistance": "high",
        "recommended_filler_min": 65,
        "notes": "Требуются композиты с повышенной прочностью и износостойкостью"
      },
      "3": {
        "name": "Grade 3",
        "description": "Средняя степень - от 1/3 до 2/3 коронки",
        "depth": "> 1/3 < 2/3 коронки",
        "tissues": "Значительный дентин",
        "characteristics": "Выраженное стирание, утрата эмали и значительной части дентина, потеря высоты коронки > 1/3 < 2/3",
        "clinical_significance": "Боли, гиперестезия, компенсаторные изменения ВНЧС, отчётливое снижение высоты прикуса",
        "recommended_microhardness_min": 70,
        "recommended_wear_resistance": "very_high",
        "recommended_filler_min": 70,
        "notes": "Критическая стадия, требуются композиты максимальной прочности"
      },
      "4": {
        "name": "Grade 4",
        "description": "Тяжёлая степень - более 2/3 коронки",
        "depth": "≥ 2/3 коронки",
        "tissues": "Вплоть до пульпы",
        "characteristics": "Почти полное стирание коронок, потеря высоты коронки ≥ 2/3, возможное вскрытие полости зуба",
        "clinical_significance": "Выраженная функциональная и эстетическая катастрофа, тяжёлые окклюзионные нарушения, обязательное комплексное ортопедическое лечение",
        "recommended_microhardness_min": 75,
        "recommended_wear_resistance": "very_high",
        "recommended_filler_min": 75,
        "notes": "Тяжёлая стадия, требуются композиты максимальной прочности, часто требуется ортопедическое лечение"
      }
    }
  },
  "bushan_classification": {
    "description": "Классификация патологической стираемости зубов по Бушану М.Г. - наиболее распространённая классификация в клинической практике",
    "degrees": {
      "I": {
        "name": "I степень",
        "depth": "В пределах эмали",
        "tissues": "Эмаль",
        "characteristics": "Стирание в пределах эмали, сглаживание бугров и режущих краёв, дентин не обнажён",
        "clinical_significance": "Функциональная перегрузка, начальные окклюзионные нарушения, часто бессимптомна",
        "recommended_microhardness_min": 50,
        "recommended_wear_resistance": "high",
        "recommended_filler_min": 60,
        "notes": "Начальная стадия, композиты с хорошей износостойкостью"
      },
      "II": {
        "name": "II степень",
        "depth": "До 1/3 коронковой части",
        "tissues": "Эмаль + дентин",
        "characteristics": "Стирание эмали, обнажение дентина, глубина до 1/3 коронковой части зуба",
        "clinical_significance": "Повышенная чувствительность, изменение высоты бугров, начальное снижение высоты прикуса",
        "recommended_microhardness_min": 60,
        "recommended_wear_resistance": "high",
        "recommended_filler_min": 65,
        "notes": "Требуются композиты с повышенной прочностью и износостойкостью"
      },
      "III": {
        "name": "III степень",
        "depth": "До 2/3 коронковой части",
        "tissues": "Значительный дентин",
        "characteristics": "Выраженное стирание, утрата эмали и значительной части дентина, глубина до 2/3 коронковой части, пульпа приближается к поверхности",
        "clinical_significance": "Боли, гиперестезия, компенсаторные изменения ВНЧС, отчётливое снижение высоты прикуса",
        "recommended_microhardness_min": 70,
        "recommended_wear_resistance": "very_high",
        "recommended_filler_min": 70,
        "notes": "Критическая стадия, требуются композиты максимальной прочности"
      },
      "IV": {
        "name": "IV степень",
        "depth": "Почти вся коронка",
        "tissues": "Вплоть до пульпы",
        "characteristics": "Почти полное стирание коронок, возможное вскрытие полости зуба, сохранены только корни или их культевые части",
        "clinical_significance": "Выраженная функциональная и эстетическая катастрофа, тяжёлые окклюзионные нарушения, обязательное комплексное ортопедическое лечение",
        "recommended_microhardness_min": 75,
        "recommended_wear_resistance": "very_high",
        "recommended_filler_min": 75,
        "notes": "Тяжёлая стадия, требуются композиты максимальной прочности, часто требуется ортопедическое лечение"
      }
    }
  },
  "regions": {
    "USA": {
      "description": "США - широкий спектр нанокомпозитов и микрогибридных композитов",
      "popular_categories": [
        "nanocomposite",
        "microhybrid",
        "high_viscosity_bulk_fill"
      ]
    },
    "Russia": {
      "description": "Россия - отечественные и импортные микрогибридные композиты",
      "popular_categories": [
        "microhybrid",
        "nanocomposite"
      ]
    },
    "Italy": {
      "description": "Италия - европейские производители, нанокомпозиты и микрогибриды",
      "popular_categories": [
        "nanocomposite",
        "microhybrid"
      ]
    },
    "Asia": {
      "description": "Азия - японские производители, высококачественные нанокомпозиты",
      "popular_categories": [
        "nanocomposite",
        "microhybrid"
      ]
    },
    "Europe": {
      "description": "Европа - широкий спектр европейских производителей (Германия, Франция, Швейцария, Италия и др.)",
      "popular_categories": [
        "nanocomposite",
        "microhybrid",
        "high_viscosity_bulk_fill"
      ],
      "countries": [
        "Germany",
        "France",
        "Switzerland",
        "Italy",
        "UK",
        "Scandinavia"
      ],
      "manufacturers": [
        "Septodont",
        "COLTENE",
        "Voco",
        "Ivoclar Vivadent",
        "Heraeus Kulzer",
        "Bredent",
        "MEGADENTA",
        "DMG",
        "Schütz Dental"
      ]
    }
  }
}